<?xml version="1.0" encoding="Windows-1252"?>
<LevelCollection xmlns:xsi="http://www.w3.org/2001/XMLSchema-instance" xmlns:xsd="http://www.w3.org/2001/XMLSchema">
  <CaveList>
    <Cave>
      <TopIndex>1000</TopIndex>
      <BottomIndex>1000</BottomIndex>
      <bTopSecretPath>false</bTopSecretPath>
      <bBottomSecretPath>false</bBottomSecretPath>
      <Moths />
    </Cave>
    <Cave>
      <TopIndex>2</TopIndex>
      <BottomIndex>1</BottomIndex>
      <bTopSecretPath>false</bTopSecretPath>
      <bBottomSecretPath>false</bBottomSecretPath>
      <Moths />
    </Cave>
    <Cave>
      <TopIndex>0</TopIndex>
      <BottomIndex>0</BottomIndex>
      <bTopSecretPath>false</bTopSecretPath>
      <bBottomSecretPath>false</bBottomSecretPath>
      <Moths>
        <MothType>
          <SpawnTransform>
            <Pos>
              <x>-1.48000336</x>
              <y>1.27</y>
            </Pos>
            <Scale>
              <x>1</x>
              <y>1</y>
            </Scale>
            <Rotation>
              <x>0</x>
              <y>0</y>
              <z>0</z>
              <w>1</w>
              <eulerAngles>
                <x>0</x>
                <y>0</y>
                <z>0</z>
              </eulerAngles>
            </Rotation>
          </SpawnTransform>
          <Colour>Green</Colour>
          <PathType>Infinity</PathType>
        </MothType>
        <MothType>
          <SpawnTransform>
            <Pos>
              <x>9.149998</x>
              <y>1.44</y>
            </Pos>
            <Scale>
              <x>1</x>
              <y>1</y>
            </Scale>
            <Rotation>
              <x>0</x>
              <y>0</y>
              <z>0</z>
              <w>1</w>
              <eulerAngles>
                <x>0</x>
                <y>0</y>
                <z>0</z>
              </eulerAngles>
            </Rotation>
          </SpawnTransform>
          <Colour>Green</Colour>
          <PathType>Clover</PathType>
        </MothType>
      </Moths>
    </Cave>
    <Cave>
      <TopIndex>1002</TopIndex>
      <BottomIndex>1002</BottomIndex>
      <bTopSecretPath>false</bTopSecretPath>
      <bBottomSecretPath>false</bBottomSecretPath>
      <Moths />
    </Cave>
  </CaveList>
  <Clumsy>
    <Pos>
      <x>0</x>
      <y>0</y>
    </Pos>
    <Scale>
      <x>0</x>
      <y>0</y>
    </Scale>
    <Rotation>
      <x>0</x>
      <y>0</y>
      <z>0</z>
      <w>0</w>
      <eulerAngles>
        <x>0</x>
        <y>0</y>
        <z>0</z>
      </eulerAngles>
    </Rotation>
  </Clumsy>
</LevelCollection>